lucy/__init__.py
lucy/auth.py
lucy/browser.py
lucy/main.py
lucy/types.py
lucy/utils.py
lucy/config/__init__.py
lucy/config/commons.py
lucy/config/config.py
lucy/config/impl.py
lucy/config/recent_tests.py
lucy/config/snippets.py
lucy/config/storage.py
lucy/config/test.py
lucy/config/user.py
lucy/config/website.py
lucy/data/__init__.py
lucy/data/template_cpp.cpp
lucy/ops/__init__.py
lucy/ops/setup.py
lucy/ops/snippets.py
lucy/ops/submit.py
lucy/ops/testing.py
lucy/params/__init__.py
lucy/params/args.py
lucy/params/opts.py
lucy01-2.0.0.dist-info/METADATA
lucy01-2.0.0.dist-info/WHEEL
lucy01-2.0.0.dist-info/entry_points.txt
lucy01-2.0.0.dist-info/top_level.txt
lucy01-2.0.0.dist-info/RECORD
