Metadata-Version: 2.1
Name: lucy01
Version: 2.0.0
Summary: CLI companion for CP.
Author-email: Mehul Todi <mehul116.dev@gmail.com>
Project-URL: Documentation, https://lucy01.readthedocs.io/en/latest/
Project-URL: Repository, https://github.com/kid-116/Lucy
Project-URL: Issues, https://github.com/kid-116/Lucy/issues
Keywords: cp,cli,companion,atcoder,codeforces,tester,snippets,lucy
Classifier: Development Status :: 4 - Beta
Classifier: Programming Language :: Python :: 3.10
Classifier: Operating System :: POSIX :: Linux
Classifier: Intended Audience :: Education
Classifier: Topic :: Education
Requires-Python: >=3.10
Requires-Dist: bs4
Requires-Dist: click
Requires-Dist: lxml
Requires-Dist: python-dotenv
Requires-Dist: requests
Requires-Dist: selenium
Provides-Extra: lint
Requires-Dist: mypy ; extra == 'lint'
Requires-Dist: pylint ; extra == 'lint'
Requires-Dist: pylint[spelling] ; extra == 'lint'
Requires-Dist: yapf ; extra == 'lint'
Provides-Extra: test
Requires-Dist: pytest ; extra == 'test'
Requires-Dist: pytest-datadir ; extra == 'test'
